console/__init__.py
console/console.py
vb_console-1.1.2.dist-info/LICENCE
vb_console-1.1.2.dist-info/METADATA
vb_console-1.1.2.dist-info/WHEEL
vb_console-1.1.2.dist-info/top_level.txt
vb_console-1.1.2.dist-info/RECORD
