Metadata-Version: 2.1
Name: vb-console
Version: 1.1.2
Summary: Logger and object inspector for Python
Home-page: https://github.com/vbyazilim/vb-console
Author: vb YAZILIM
Author-email: hello@vbyazilim.com
License: MIT
Project-URL: VB YAZILIM, https://vbyazilim.com
Project-URL: Source, https://github.com/vbyazilim/vb-console
Keywords: vbyazilim,console,debug,log,test
Platform: UNKNOWN
Classifier: License :: OSI Approved :: MIT License
Classifier: Operating System :: OS Independent
Classifier: Development Status :: 5 - Production/Stable
Classifier: Programming Language :: Python :: 3
Classifier: Programming Language :: Python :: 3 :: Only
Classifier: Topic :: Utilities
Classifier: Topic :: Software Development :: Libraries :: Python Modules
Requires-Python: >=3.0
License-File: LICENCE
